webhdfs/__init__.py
webhdfs/cli.py
webhdfs/webhdfs.py
webhdfs_client-0.1.0.dist-info/LICENSE
webhdfs_client-0.1.0.dist-info/METADATA
webhdfs_client-0.1.0.dist-info/WHEEL
webhdfs_client-0.1.0.dist-info/entry_points.txt
webhdfs_client-0.1.0.dist-info/top_level.txt
webhdfs_client-0.1.0.dist-info/RECORD
