Metadata-Version: 2.1
Name: webhdfs-client
Version: 0.1.0
Summary: A WebHDFS Client
Home-page: https://github.com/luff/webhdfs-client
Author: Lu.Yi
Author-email: luyiff@gmail.com
License: UNKNOWN
Platform: UNKNOWN
Classifier: License :: OSI Approved :: MIT License
Classifier: Operating System :: POSIX
Requires-Dist: click
Requires-Dist: requests (>=2.12.0)
